kintera/__init__.py
kintera/chemtable.py
kintera/kininput.py
kintera/kintera.cpython-312-x86_64-linux-gnu.so
kintera/kintera.pyi
kintera/py.typed
kintera/api/__init__.py
kintera/kintera/CMakeLists.txt
kintera/kintera/add_arg.h
kintera/kintera/constants.h
kintera/kintera/func_table.cpp
kintera/kintera/func_table.cu
kintera/kintera/kintera_formatter.hpp
kintera/kintera/loops.cuh
kintera/kintera/reaction.cpp
kintera/kintera/reaction.hpp
kintera/kintera/species.cpp
kintera/kintera/species.hpp
kintera/kintera/kinetics/arrhenius.cpp
kintera/kintera/kinetics/arrhenius.hpp
kintera/kintera/kinetics/coagulation.cpp
kintera/kintera/kinetics/coagulation.hpp
kintera/kintera/kinetics/evaporation.cpp
kintera/kintera/kinetics/evaporation.hpp
kintera/kintera/kinetics/evolve_implicit.hpp
kintera/kintera/kinetics/jacobian.hpp
kintera/kintera/kinetics/jacobian_evaporation.cpp
kintera/kintera/kinetics/jacobian_mass_action.cpp
kintera/kintera/kinetics/kinetics.cpp
kintera/kintera/kinetics/kinetics.hpp
kintera/kintera/kinetics/kinetics_formatter.hpp
kintera/kintera/kinetics/kinetics_options.cpp
kintera/kintera/kinetics/rate_constant.cpp
kintera/kintera/kinetics/rate_constant.hpp
kintera/kintera/kinetics/species_rate.hpp
kintera/kintera/math/core.h
kintera/kintera/math/interpolation.cpp
kintera/kintera/math/interpolation.hpp
kintera/kintera/math/leastsq.h
kintera/kintera/math/leastsq_kkt.h
kintera/kintera/math/lubksb.h
kintera/kintera/math/ludcmp.h
kintera/kintera/math/luminv.h
kintera/kintera/math/psolve.h
kintera/kintera/math/swap.h
kintera/kintera/photo/photo_opacity.hpp
kintera/kintera/photo/photo_opacity.hpp_
kintera/kintera/photo/photolysis.cpp
kintera/kintera/photo/photolysis.cpp_
kintera/kintera/photo/photolysis.h
kintera/kintera/photo/photolysis.h_
kintera/kintera/solver/explicit.cpp
kintera/kintera/solver/explicit.h
kintera/kintera/thermo/equilibrate_tp.h
kintera/kintera/thermo/equilibrate_uv.h
kintera-1.2.9.dist-info/METADATA
kintera-1.2.9.dist-info/WHEEL
kintera-1.2.9.dist-info/top_level.txt
kintera-1.2.9.dist-info/RECORD
kintera-1.2.9.dist-info/licenses/LICENSE
kintera-1.2.9.dist-info/sboms/auditwheel.cdx.json
