Metadata-Version: 2.4
Name: kintera
Version: 1.2.9
Summary: Atmospheric Chemistry and Thermodynamics Library
Author-email: Cheng Li <chengcli@umich.edu>, Sihe Chen <sihechen@caltech.edu>
License: LICENSE
Project-URL: Homepage, https://github.com/chengcli/kintera
Project-URL: Documentation, https://kintera.readthedocs.io
Classifier: Development Status :: 3 - Alpha
Classifier: Intended Audience :: Science/Research
Classifier: Natural Language :: English
Classifier: Programming Language :: C
Classifier: Programming Language :: C++
Classifier: Programming Language :: Python :: 3.9
Classifier: Programming Language :: Python :: 3.10
Classifier: Programming Language :: Python :: 3.11
Classifier: Programming Language :: Python :: Implementation :: CPython
Classifier: Topic :: Scientific/Engineering :: Atmospheric Science
Classifier: Topic :: Scientific/Engineering :: Physics
Classifier: Topic :: Scientific/Engineering :: Astronomy
Requires-Python: >=3.9
License-File: LICENSE
Requires-Dist: numpy
Requires-Dist: pyharp>=1.8.5
Dynamic: license-file
